gencube/__init__.py
gencube/__main__.py
gencube/constants.py
gencube/gencube_annotation.py
gencube/gencube_crossgenome.py
gencube/gencube_geneset.py
gencube/gencube_genome.py
gencube/gencube_info.py
gencube/gencube_seqmeta.py
gencube/gencube_sequence.py
gencube/main.py
gencube/note.py
gencube/utils.py
gencube-1.11.0.dist-info/licenses/LICENSE
gencube-1.11.0.dist-info/METADATA
gencube-1.11.0.dist-info/WHEEL
gencube-1.11.0.dist-info/entry_points.txt
gencube-1.11.0.dist-info/top_level.txt
gencube-1.11.0.dist-info/RECORD
