Metadata-Version: 2.4
Name: gencube
Version: 1.11.0
Summary: GenCube enables researchers to search for, download, and unify genome assemblies and diverse types of annotations, and retrieve metadata for sequencing-based experimental data suitable for specific requirements.
Author-email: Keun Hong Son <newhong@snu.ac.kr>
Maintainer-email: Keun Hong Son <newhong@snu.ac.kr>
License-Expression: MIT
Project-URL: Homepage, https://keun-hong.github.io/
Project-URL: Repository, https://github.com/snu-cdrc/gencube
Project-URL: Bugs, https://github.com/snu-cdrc/gencube/issues
Project-URL: Changelog, https://github.com/snu-cdrc/gencube/blob/master/changelog.md
Keywords: Genome,Genomic,Geneset,Annotation,Comparative,Sequencing,Metadata
Classifier: Development Status :: 4 - Beta
Classifier: Intended Audience :: Science/Research
Classifier: Topic :: Scientific/Engineering :: Bio-Informatics
Classifier: Topic :: Utilities
Classifier: Programming Language :: Python :: 3
Classifier: Programming Language :: Python :: 3.7
Classifier: Programming Language :: Python :: 3.8
Classifier: Programming Language :: Python :: 3.9
Classifier: Programming Language :: Python :: 3.10
Classifier: Programming Language :: Python :: 3.11
Classifier: Programming Language :: Python :: 3.12
Requires-Python: <4,>=3.7
License-File: LICENSE
Requires-Dist: biopython>=1.79
Requires-Dist: pandas>=1.3.0
Requires-Dist: numpy>=1.21.0
Requires-Dist: requests>=2.25.1
Requires-Dist: urllib3<3.0,>=1.26.5
Requires-Dist: xmltodict>=0.12.0
Requires-Dist: beautifulsoup4>=4.9.3
Requires-Dist: tqdm>=4.61.2
Requires-Dist: tabulate>=0.8.9
Provides-Extra: dev
Requires-Dist: coverage; extra == "dev"
Requires-Dist: mypy; extra == "dev"
Requires-Dist: pytest; extra == "dev"
Requires-Dist: ruff; extra == "dev"
Dynamic: license-file
